{
  "timestamp": "2026-05-05T15:59:03Z",
  "sources_used": [
    "cnn",
    "own"
  ],
  "total_unique_posts": 19386,
  "in_all_sources": 9,
  "partial_match": 19377,
  "new_deletions": 0,
  "total_known_deletions": 0,
  "partial_details": [
    {
      "content_preview": "Beautiful family. 🇺🇸",
      "created_at": "2022-11-14T22:02:00.000Z",
      "url": "https://truthsocial.com/@OksanaTrump/109345593973985731",
      "present_in": [
        "own"
      ],
      "missing_from": [
        "cnn"
      ],
      "truth_social_status": "blocked"
    },
    {
      "content_preview": "Final certification!",
      "created_at": "2024-04-15T10:38:00.000Z",
      "url": "https://truthsocial.com/@realDonaldTrump/112275745892106221",
      "present_in": [
        "own"
      ],
      "missing_from": [
        "cnn"
      ],
      "truth_social_status": "blocked"
    },
    {
      "content_preview": "Donald Trump continues to dominate the GOP primary field while also crushing Biden.https://www.westernjournal.com/trump-",
      "created_at": "2023-06-18T12:02:00.000Z",
      "url": "https://truthsocial.com/@western_journal/110566055886081834",
      "present_in": [
        "own"
      ],
      "missing_from": [
        "cnn"
      ],
      "truth_social_status": "blocked"
    },
    {
      "content_preview": "THANK YOU WILDWOOD, NEW JERSEY—MAGA2024! https://www.DonaldJTrump.com",
      "created_at": "2024-05-11T20:04:00.000Z",
      "url": "https://truthsocial.com/@realDonaldTrump/112425189365761634",
      "present_in": [
        "own"
      ],
      "missing_from": [
        "cnn"
      ],
      "truth_social_status": "blocked"
    },
    {
      "content_preview": "https://thenationalpulse.com/2024/01/28/snoop-dogg-now-says-he-has-nothing-but-love-and-respect-for-donald-trump/",
      "created_at": "2024-01-28T13:53:00.000Z",
      "url": "https://truthsocial.com/@realDonaldTrump/111835086528156540",
      "present_in": [
        "own"
      ],
      "missing_from": [
        "cnn"
      ],
      "truth_social_status": "blocked"
    },
    {
      "content_preview": "I am proud to announce that we will be hosting a magnificent Parade to honor the United States Army’s 250th Birthday, on",
      "created_at": "2025-05-23T19:25:52.673Z",
      "url": "https://truthsocial.com/@realDonaldTrump/114558786117625961",
      "present_in": [
        "cnn"
      ],
      "missing_from": [
        "own"
      ],
      "truth_social_status": "blocked"
    },
    {
      "content_preview": "CHINA IS LAUGHING AT US. THEY ARE VERY HAPPY!!!",
      "created_at": "2023-03-22T16:23:00.000Z",
      "url": "https://truthsocial.com/@realDonaldTrump/110068802289558017",
      "present_in": [
        "own"
      ],
      "missing_from": [
        "cnn"
      ],
      "truth_social_status": "blocked"
    },
    {
      "content_preview": "It should be “Trump,” and our Country will be Great Again—and fast! https://www.americanthinker.com/articles/2022/11/sho",
      "created_at": "2022-11-29T17:39:00.000Z",
      "url": "https://truthsocial.com/@realDonaldTrump/109429495965545494",
      "present_in": [
        "own"
      ],
      "missing_from": [
        "cnn"
      ],
      "truth_social_status": "blocked"
    },
    {
      "content_preview": "Admiral Ronny Jackson is an America First Patriot, a fantastic Doctor, and an incredible Congressman for the people of T",
      "created_at": "2024-03-02T12:37:00.000Z",
      "url": "https://truthsocial.com/@realDonaldTrump/112027308490531958",
      "present_in": [
        "own"
      ],
      "missing_from": [
        "cnn"
      ],
      "truth_social_status": "blocked"
    },
    {
      "content_preview": "https://truthsocial.com/@realDonaldTrump/114950348792604159",
      "created_at": "2025-08-01T02:03:58.602Z",
      "url": "https://truthsocial.com/@realDonaldTrump/114951050923974932",
      "present_in": [
        "cnn"
      ],
      "missing_from": [
        "own"
      ],
      "truth_social_status": "blocked"
    },
    {
      "content_preview": "I am voting for world peace: #Trump2024",
      "created_at": "2024-05-08T16:12:00.000Z",
      "url": "https://truthsocial.com/@ILoveAmericaNews/112407291932801150",
      "present_in": [
        "own"
      ],
      "missing_from": [
        "cnn"
      ],
      "truth_social_status": "blocked"
    },
    {
      "content_preview": "Tremendous WIN in the great State of Utah for Mayor Trent Staggs, who has just received the Endorsement of the Utah Repu",
      "created_at": "2024-04-28T17:09:00.000Z",
      "url": "https://truthsocial.com/@realDonaldTrump/112350893788689819",
      "present_in": [
        "own"
      ],
      "missing_from": [
        "cnn"
      ],
      "truth_social_status": "blocked"
    },
    {
      "content_preview": "Former Federal Agents, and others, claim retaliation by the FBI and DOJ. Gee, who would ever think such a thing could ha",
      "created_at": "2023-05-19T00:30:00.000Z",
      "url": "https://truthsocial.com/@realDonaldTrump/110393466631056505",
      "present_in": [
        "own"
      ],
      "missing_from": [
        "cnn"
      ],
      "truth_social_status": "blocked"
    },
    {
      "content_preview": "https://thenationalpulse.com/2023/10/10/biden-has-let-over-70000-illegals-from-muslim-countries-into-u-s-in-2-years/",
      "created_at": "2023-11-28T20:10:00.000Z",
      "url": "https://truthsocial.com/@realDonaldTrump/111491169339516471",
      "present_in": [
        "own"
      ],
      "missing_from": [
        "cnn"
      ],
      "truth_social_status": "blocked"
    },
    {
      "content_preview": "TOGETHER—WE WILL MAKE AMERICA SAFE &amp; GREAT AGAIN! https://www.DonaldJTrump.com",
      "created_at": "2024-04-17T18:42:00.000Z",
      "url": "https://truthsocial.com/@realDonaldTrump/112288973678097435",
      "present_in": [
        "own"
      ],
      "missing_from": [
        "cnn"
      ],
      "truth_social_status": "blocked"
    },
    {
      "content_preview": "The Obamacare secret at the heart of the shutdown: insurers made billions at taxpayer expense:https://justthenews.com/go",
      "created_at": "2025-11-11T04:20:04.663Z",
      "url": "https://truthsocial.com/@realDonaldTrump/115529141758455385",
      "present_in": [
        "cnn"
      ],
      "missing_from": [
        "own"
      ],
      "truth_social_status": "blocked"
    },
    {
      "content_preview": "Based on a thorough, detailed, and complete review of the ridiculous, poorly written, and extraordinarily anti-American ",
      "created_at": "2026-02-21T15:59:33.498Z",
      "url": "https://truthsocial.com/@realDonaldTrump/116109447886304328",
      "present_in": [
        "cnn"
      ],
      "missing_from": [
        "own"
      ],
      "truth_social_status": "blocked"
    },
    {
      "content_preview": "It’s becoming more and more obvious to me why the “Crazed” Democrats are allowing millions and millions of totally unvet",
      "created_at": "2023-12-30T00:23:00.000Z",
      "url": "https://truthsocial.com/@realDonaldTrump/111667694816747840",
      "present_in": [
        "own"
      ],
      "missing_from": [
        "cnn"
      ],
      "truth_social_status": "blocked"
    },
    {
      "content_preview": "Remember all of the Fake News reporting that was done saying that Crooked Joe Biden was fully cooperating with the Rober",
      "created_at": "2023-08-26T15:52:00.000Z",
      "url": "https://truthsocial.com/@realDonaldTrump/110957662248028763",
      "present_in": [
        "own"
      ],
      "missing_from": [
        "cnn"
      ],
      "truth_social_status": "blocked"
    },
    {
      "content_preview": "#FJB #TrumpWon2020 #Trump2024Landslide #ArrestBiden #ArrestObama #DeathPenaltyForPedophiles #MilitaryTribunalsForTreason",
      "created_at": "2024-04-24T19:08:00.000Z",
      "url": "https://truthsocial.com/@TrutherThinkTank/112328710901608299",
      "present_in": [
        "own"
      ],
      "missing_from": [
        "cnn"
      ],
      "truth_social_status": "blocked"
    },
    {
      "content_preview": "Don Lemon has been a loser from Day One, has zero credibility. He is a negative ratings machine, and always will be. The",
      "created_at": "2023-01-26T18:26:00.000Z",
      "url": "https://truthsocial.com/@realDonaldTrump/109758093544731065",
      "present_in": [
        "own"
      ],
      "missing_from": [
        "cnn"
      ]
    },
    {
      "content_preview": "RT @CrazyCatRescuer#WeAreCharIieKirk #XTeam #MH8",
      "created_at": "2025-11-17T14:36:10.590Z",
      "url": "https://truthsocial.com/@realDonaldTrump/115565538219866607",
      "present_in": [
        "cnn"
      ],
      "missing_from": [
        "own"
      ]
    },
    {
      "content_preview": "https://www.thegatewaypundit.com/2023/04/new-zealands-strongest-man-to-compete-in-womens-powerlifting-contest-to-protest",
      "created_at": "2023-04-23T13:01:00.000Z",
      "url": "https://truthsocial.com/@realDonaldTrump/110249200028763169",
      "present_in": [
        "own"
      ],
      "missing_from": [
        "cnn"
      ]
    },
    {
      "content_preview": "TO MY GREAT FELLOW AMERICANS…",
      "created_at": "2025-09-11T00:44:20.881Z",
      "url": "https://truthsocial.com/@realDonaldTrump/115182892535295750",
      "present_in": [
        "cnn"
      ],
      "missing_from": [
        "own"
      ]
    },
    {
      "content_preview": "I joined “60 Minutes” with Crooked Joe Biden!",
      "created_at": "2023-10-15T22:31:00.000Z",
      "url": "https://truthsocial.com/@realDonaldTrump/111242347183608595",
      "present_in": [
        "own"
      ],
      "missing_from": [
        "cnn"
      ]
    },
    {
      "content_preview": "The American ChristmasHandcrafted #Christmas OrnamentsMade in the #USA Each purchase includes an #NFT Order by October 2",
      "created_at": "2022-09-23T08:29:00.000Z",
      "url": "https://truthsocial.com/@USAmemorabilia/109047719779354441",
      "present_in": [
        "own"
      ],
      "missing_from": [
        "cnn"
      ]
    },
    {
      "content_preview": "Big Rally in Arizona Friday evening. See you there!",
      "created_at": "2022-07-21T07:59:00.000Z",
      "url": "https://truthsocial.com/@realDonaldTrump/108685214485871925",
      "present_in": [
        "own"
      ],
      "missing_from": [
        "cnn"
      ]
    },
    {
      "content_preview": "Whether the Fake News Media likes admitting it or not, there was tremendous misrepresentation and lies in that Speech, b",
      "created_at": "2024-03-07T22:38:00.000Z",
      "url": "https://truthsocial.com/@realDonaldTrump/112057983606479373",
      "present_in": [
        "own"
      ],
      "missing_from": [
        "cnn"
      ]
    },
    {
      "content_preview": "The Unselects are going against me because I am the only one who can fix our endangered Country, and they want to DESTRO",
      "created_at": "2022-06-14T08:05:00.000Z",
      "url": "https://truthsocial.com/@realDonaldTrump/108475734630887783",
      "present_in": [
        "own"
      ],
      "missing_from": [
        "cnn"
      ]
    },
    {
      "content_preview": "https://thenationalpulse.com/2023/05/23/apple-makes-multi-billion-dollar-us-chips-deal-with-firm-trump-lured-over-in-201",
      "created_at": "2023-06-05T13:33:00.000Z",
      "url": "https://truthsocial.com/@realDonaldTrump/110492806003269892",
      "present_in": [
        "own"
      ],
      "missing_from": [
        "cnn"
      ]
    },
    {
      "content_preview": "Why was the wonderful Turning Point under INVESTIGATION by \"Deranged\" Jack Smith and the Corrupt & Incompetent Biden Adm",
      "created_at": "2025-09-17T02:23:35.554Z",
      "url": "https://truthsocial.com/@realDonaldTrump/115217256645822887",
      "present_in": [
        "cnn"
      ],
      "missing_from": [
        "own"
      ]
    },
    {
      "content_preview": "The Great Gary Player: “Turnberry is, without a question, in the Top Five Greatest Golf Courses I’ve ever played in my 7",
      "created_at": "2025-07-26T18:57:43.150Z",
      "url": "https://truthsocial.com/@realDonaldTrump/114921063256769586",
      "present_in": [
        "cnn"
      ],
      "missing_from": [
        "own"
      ]
    },
    {
      "content_preview": "REPORTER TO MIKE JOHNSON: “You helped lead the effort to overturn the 2020 election results, do you..”☝🏻🤓GOP: *BOO* “SHU",
      "created_at": "2023-10-25T01:36:00.000Z",
      "url": "https://truthsocial.com/@alx/111294034308807610",
      "present_in": [
        "own"
      ],
      "missing_from": [
        "cnn"
      ]
    },
    {
      "content_preview": "https://www.americanthinker.com/blog/2024/03/trump_towers_in_his_mastery_of_words_to_rally_voters.html",
      "created_at": "2024-04-12T11:04:00.000Z",
      "url": "https://truthsocial.com/@realDonaldTrump/112258859363297478",
      "present_in": [
        "own"
      ],
      "missing_from": [
        "cnn"
      ]
    },
    {
      "content_preview": "Government funding runs out next week, and Democrats are threatening to shut down the Government - But I am working with",
      "created_at": "2025-03-06T00:20:21.964Z",
      "url": "https://truthsocial.com/@realDonaldTrump/114112621570651215",
      "present_in": [
        "cnn"
      ],
      "missing_from": [
        "own"
      ]
    },
    {
      "content_preview": "Numbers recently released show that TARIFFS have reduced the Trade Deficit of the United States by more than half. This ",
      "created_at": "2025-12-16T23:15:01.678Z",
      "url": "https://truthsocial.com/@realDonaldTrump/115731785428395132",
      "present_in": [
        "cnn"
      ],
      "missing_from": [
        "own"
      ]
    },
    {
      "content_preview": "🚨🚨 NY POST: NY Republican Rep. Elise Stefanik rakes in $2M in latest round of fundraising, $5M total this yearI'm incred",
      "created_at": "2023-07-09T17:16:00.000Z",
      "url": "https://truthsocial.com/@elisestefanik/110686199710116399",
      "present_in": [
        "own"
      ],
      "missing_from": [
        "cnn"
      ]
    },
    {
      "content_preview": "https://www.rsbnetwork.com/news/trump-the-more-we-win-by-the-bigger-a-signal-we-send-for-november/",
      "created_at": "2024-01-22T23:13:00.000Z",
      "url": "https://truthsocial.com/@realDonaldTrump/111803315049374828",
      "present_in": [
        "own"
      ],
      "missing_from": [
        "cnn"
      ]
    },
    {
      "content_preview": "Helen Kerwin is running in Texas State House District 58 against RINO DeWayne Burns, who has one of the most liberal vot",
      "created_at": "2024-05-27T11:51:00.000Z",
      "url": "https://truthsocial.com/@realDonaldTrump/112513848940452439",
      "present_in": [
        "own"
      ],
      "missing_from": [
        "cnn"
      ]
    },
    {
      "content_preview": "THE MOST HISTORIC 100 HOURS IN AMERICAN HISTORY—THE GOLDEN AGE OF AMERICA BEGINS RIGHT NOW!",
      "created_at": "2025-01-24T22:02:01.840Z",
      "url": "https://truthsocial.com/@realDonaldTrump/113885585200862094",
      "present_in": [
        "cnn"
      ],
      "missing_from": [
        "own"
      ]
    },
    {
      "content_preview": "We owe our children GREAT schools that lead to incredible jobs, so that they can have a wonderful life. I want them to b",
      "created_at": "2023-08-31T17:41:00.000Z",
      "url": "https://truthsocial.com/@realDonaldTrump/110986400865532875",
      "present_in": [
        "own"
      ],
      "missing_from": [
        "cnn"
      ]
    },
    {
      "content_preview": "When is \"enough, enough\" for our Republican Senators. There comes a time when you must do what should have been done a l",
      "created_at": "2026-03-26T10:51:59.209Z",
      "url": "https://truthsocial.com/@realDonaldTrump/116295094711655881",
      "present_in": [
        "cnn"
      ],
      "missing_from": [
        "own"
      ]
    },
    {
      "content_preview": "Tomorrow my wonderful and beautiful daughter, Ivanka, is going to the Lower Manhattan Courthouse, at the direction of Le",
      "created_at": "2023-11-08T00:15:00.000Z",
      "url": "https://truthsocial.com/@realDonaldTrump/111373225096610033",
      "present_in": [
        "own"
      ],
      "missing_from": [
        "cnn"
      ]
    },
    {
      "content_preview": "I got a call from a very good guy, and friend of mine, Kid Rock, asking me whether or not it would be possible for me to",
      "created_at": "2025-03-30T23:49:25.763Z",
      "url": "https://truthsocial.com/@realDonaldTrump/114254057682596962",
      "present_in": [
        "cnn"
      ],
      "missing_from": [
        "own"
      ]
    },
    {
      "content_preview": "I just played a round of Golf with Alexander Stubb, President of Finland. He is a very good player, and we won the Men’s",
      "created_at": "2025-03-29T20:14:54.826Z",
      "url": "https://truthsocial.com/@realDonaldTrump/114247551865595874",
      "present_in": [
        "cnn"
      ],
      "missing_from": [
        "own"
      ]
    },
    {
      "content_preview": "https://x.com/willsmi1/status/1989828332704395618?s=46",
      "created_at": "2025-11-17T05:23:01.533Z",
      "url": "https://truthsocial.com/@realDonaldTrump/115563363141806280",
      "present_in": [
        "cnn"
      ],
      "missing_from": [
        "own"
      ]
    },
    {
      "content_preview": "RT @TeamTrumpPresident Trump delivers remarks during a candlelight dinner at the National Building Museum in Washington,",
      "created_at": "2025-01-20T04:52:34.159Z",
      "url": "https://truthsocial.com/@realDonaldTrump/113858887952515391",
      "present_in": [
        "cnn"
      ],
      "missing_from": [
        "own"
      ]
    },
    {
      "content_preview": "https://thefederalist.com/2025/01/17/trump-should-pardon-d-c-s-good-cops-victimized-by-bidens-soft-on-crime-doj/",
      "created_at": "2025-01-21T22:37:31.505Z",
      "url": "https://truthsocial.com/@realDonaldTrump/113868737839409109",
      "present_in": [
        "cnn"
      ],
      "missing_from": [
        "own"
      ]
    },
    {
      "content_preview": "“Exclusive — House GOP Campaign Chief Thanks Trump for Investing in Midterms: ‘Tremendous Partner’” https://www.breitbar",
      "created_at": "2022-09-29T13:16:00.000Z",
      "url": "https://truthsocial.com/@realDonaldTrump/109082822890536211",
      "present_in": [
        "own"
      ],
      "missing_from": [
        "cnn"
      ]
    },
    {
      "content_preview": "Page Two: The only way Otto could have been saved is if President Obama and Crooked Joe saved him early. The only reason",
      "created_at": "2024-01-22T19:14:00.000Z",
      "url": "https://truthsocial.com/@realDonaldTrump/111802377172090827",
      "present_in": [
        "own"
      ],
      "missing_from": [
        "cnn"
      ]
    }
  ]
}